<?xml version="1.0" encoding="UTF-8"?>
<metadata xml:lang="en"><Esri><CreaDate>20200708</CreaDate><CreaTime>12124100</CreaTime><ArcGISFormat>1.0</ArcGISFormat><SyncOnce>FALSE</SyncOnce><DataProperties><lineage><Process ToolSource="c:\program files (x86)\arcgis\desktop10.8\ArcToolbox\Toolboxes\Data Management Tools.tbx\CalculateField" Date="20200708" Time="121241">CalculateField SOM_AttReclass att1recl "Younger" VB #</Process><Process ToolSource="c:\program files (x86)\arcgis\desktop10.8\ArcToolbox\Toolboxes\Data Management Tools.tbx\CalculateField" Date="20200708" Time="121432">CalculateField SOM_AttReclass att1recl "Older" VB #</Process><Process ToolSource="c:\program files (x86)\arcgis\desktop10.8\ArcToolbox\Toolboxes\Data Management Tools.tbx\CalculateField" Date="20200708" Time="121735">CalculateField SOM_AttReclass att2recl "Female" VB #</Process><Process ToolSource="c:\program files (x86)\arcgis\desktop10.8\ArcToolbox\Toolboxes\Data Management Tools.tbx\CalculateField" Date="20200708" Time="121847">CalculateField SOM_AttReclass att2recl "Male" VB #</Process><Process ToolSource="c:\program files (x86)\arcgis\desktop10.8\ArcToolbox\Toolboxes\Data Management Tools.tbx\CalculateField" Date="20200708" Time="122144">CalculateField SOM_AttReclass att10recl "High BMI" VB #</Process><Process ToolSource="c:\program files (x86)\arcgis\desktop10.8\ArcToolbox\Toolboxes\Data Management Tools.tbx\CalculateField" Date="20200708" Time="122224">CalculateField SOM_AttReclass att10recl "Low BMI" VB #</Process><Process ToolSource="c:\program files (x86)\arcgis\desktop10.8\ArcToolbox\Toolboxes\Data Management Tools.tbx\CalculateField" Date="20200708" Time="122656">CalculateField SOM_AttReclass att11recl "History of Cardiovascular Disease" VB #</Process><Process ToolSource="c:\program files (x86)\arcgis\desktop10.8\ArcToolbox\Toolboxes\Data Management Tools.tbx\CalculateField" Date="20200708" Time="122837">CalculateField SOM_AttReclass att11recl "" VB #</Process><Process ToolSource="c:\program files (x86)\arcgis\desktop10.8\ArcToolbox\Toolboxes\Data Management Tools.tbx\CalculateField" Date="20200708" Time="122907">CalculateField SOM_AttReclass att11recl "History of Cardiovascular Disease" VB #</Process><Process ToolSource="c:\program files (x86)\arcgis\desktop10.8\ArcToolbox\Toolboxes\Data Management Tools.tbx\CalculateField" Date="20200708" Time="122950">CalculateField SOM_AttReclass att12recl "Family History of Cardiovascular Disease" VB #</Process><Process ToolSource="c:\program files (x86)\arcgis\desktop10.8\ArcToolbox\Toolboxes\Data Management Tools.tbx\CalculateField" Date="20200708" Time="123037">CalculateField SOM_AttReclass att13recl "No Family History of Cardiovascular Disease" VB #</Process><Process ToolSource="c:\program files (x86)\arcgis\desktop10.8\ArcToolbox\Toolboxes\Data Management Tools.tbx\CalculateField" Date="20200708" Time="123138">CalculateField SOM_AttReclass att14recl "Unknown Family History of Cardiovascular Disease" VB #</Process><Process ToolSource="c:\program files (x86)\arcgis\desktop10.8\ArcToolbox\Toolboxes\Data Management Tools.tbx\CalculateField" Date="20200708" Time="123518">CalculateField SOM_AttReclass att15recl "Previous PCI" VB #</Process><Process ToolSource="c:\program files (x86)\arcgis\desktop10.8\ArcToolbox\Toolboxes\Data Management Tools.tbx\CalculateField" Date="20200708" Time="124222">CalculateField SOM_AttReclass att16recl "Previous Myocardial Infarction" VB #</Process><Process ToolSource="c:\program files (x86)\arcgis\desktop10.8\ArcToolbox\Toolboxes\Data Management Tools.tbx\CalculateField" Date="20200708" Time="124357">CalculateField SOM_AttReclass att17recl "Previous CABG" VB #</Process><Process ToolSource="c:\program files (x86)\arcgis\desktop10.8\ArcToolbox\Toolboxes\Data Management Tools.tbx\CalculateField" Date="20200708" Time="124446">CalculateField SOM_AttReclass att18recl "Hypertension" VB #</Process><Process ToolSource="c:\program files (x86)\arcgis\desktop10.8\ArcToolbox\Toolboxes\Data Management Tools.tbx\CalculateField" Date="20200708" Time="124540">CalculateField SOM_AttReclass att19recl "Dyslipidemia" VB #</Process><Process ToolSource="c:\program files (x86)\arcgis\desktop10.8\ArcToolbox\Toolboxes\Data Management Tools.tbx\CalculateField" Date="20200708" Time="124647">CalculateField SOM_AttReclass att20recl "Diabetes Mellitus" VB #</Process><Process ToolSource="c:\program files (x86)\arcgis\desktop10.8\ArcToolbox\Toolboxes\Data Management Tools.tbx\CalculateField" Date="20200708" Time="125622">CalculateField SOM_AttReclass att21recl "Clinical Signs of Heart Failure" VB #</Process><Process ToolSource="c:\program files (x86)\arcgis\desktop10.8\ArcToolbox\Toolboxes\Data Management Tools.tbx\CalculateField" Date="20200708" Time="125739">CalculateField SOM_AttReclass att22recl "Current Smoking" VB #</Process><Process ToolSource="c:\program files (x86)\arcgis\desktop10.8\ArcToolbox\Toolboxes\Data Management Tools.tbx\CalculateField" Date="20200708" Time="125815">CalculateField SOM_AttReclass att23recl "Former Smoking" VB #</Process><Process ToolSource="c:\program files (x86)\arcgis\desktop10.8\ArcToolbox\Toolboxes\Data Management Tools.tbx\CalculateField" Date="20200708" Time="130018">CalculateField SOM_AttReclass att24recl "Never Smoking" VB #</Process><Process ToolSource="c:\program files (x86)\arcgis\desktop10.8\ArcToolbox\Toolboxes\Data Management Tools.tbx\CalculateField" Date="20200708" Time="130130">CalculateField SOM_AttReclass att27recl "Meth Use" VB #</Process><Process ToolSource="c:\program files (x86)\arcgis\desktop10.8\ArcToolbox\Toolboxes\Data Management Tools.tbx\CalculateField" Date="20200708" Time="130235">CalculateField SOM_AttReclass att28recl "Other Drug Use" VB #</Process><Process ToolSource="c:\program files (x86)\arcgis\desktop10.8\ArcToolbox\Toolboxes\Data Management Tools.tbx\CalculateField" Date="20200708" Time="130344">CalculateField SOM_AttReclass att29recl "Previous Stroke" VB #</Process><Process ToolSource="c:\program files (x86)\arcgis\desktop10.8\ArcToolbox\Toolboxes\Data Management Tools.tbx\CalculateField" Date="20200708" Time="130504">CalculateField SOM_AttReclass att30recl "Previous TIA" VB #</Process><Process ToolSource="c:\program files (x86)\arcgis\desktop10.8\ArcToolbox\Toolboxes\Data Management Tools.tbx\CalculateField" Date="20200708" Time="130619">CalculateField SOM_AttReclass att31recl "Aspirin" VB #</Process><Process ToolSource="c:\program files (x86)\arcgis\desktop10.8\ArcToolbox\Toolboxes\Data Management Tools.tbx\CalculateField" Date="20200708" Time="130728">CalculateField SOM_AttReclass att32recl "Present Beta Blocker" VB #</Process><Process ToolSource="c:\program files (x86)\arcgis\desktop10.8\ArcToolbox\Toolboxes\Data Management Tools.tbx\CalculateField" Date="20200708" Time="130806">CalculateField SOM_AttReclass att31recl "Present Aspirin" VB #</Process><Process ToolSource="c:\program files (x86)\arcgis\desktop10.8\ArcToolbox\Toolboxes\Data Management Tools.tbx\CalculateField" Date="20200708" Time="131054">CalculateField SOM_AttReclass att33recl "Present PAI" VB #</Process><Process ToolSource="c:\program files (x86)\arcgis\desktop10.8\ArcToolbox\Toolboxes\Data Management Tools.tbx\CalculateField" Date="20200708" Time="131155">CalculateField SOM_AttReclass att34recl "Present Statins" VB #</Process><Process ToolSource="c:\program files (x86)\arcgis\desktop10.8\ArcToolbox\Toolboxes\Data Management Tools.tbx\CalculateField" Date="20200708" Time="131253">CalculateField SOM_AttReclass att35recl "Assisted Living" VB #</Process><Process ToolSource="c:\program files (x86)\arcgis\desktop10.8\ArcToolbox\Toolboxes\Data Management Tools.tbx\CalculateField" Date="20200708" Time="131525">CalculateField SOM_AttReclass att36recl "Home Health Care" VB #</Process><Process ToolSource="c:\program files (x86)\arcgis\desktop10.8\ArcToolbox\Toolboxes\Data Management Tools.tbx\CalculateField" Date="20200708" Time="131728">CalculateField SOM_AttReclass att38recl "Nursing Home" VB #</Process><Process ToolSource="c:\program files (x86)\arcgis\desktop10.8\ArcToolbox\Toolboxes\Data Management Tools.tbx\Dissolve" Date="20200708" Time="195837">Dissolve SOM_AttReclass D:\askupin\Research\2020\STEMI\2020707_LoB_SOM\1_BaseMap\2_SOM_Visualization\BaseMap_2020\data\AttributeSeparation\att22.shp att22recl # MULTI_PART DISSOLVE_LINES</Process></lineage><itemProps><itemName Sync="TRUE">att22_SimplPoly0.5</itemName><imsContentType Sync="TRUE">002</imsContentType><itemSize Sync="TRUE">0.000</itemSize><itemLocation><linkage Sync="TRUE">file://\\GEO-SKUPINLT1\D$\askupin\Research\2020\STEMI\2020707_LoB_SOM\BaseMap_2020\data\AttributeSeparation\att22_SimplPoly0.shp</linkage><protocol Sync="TRUE">Local Area Network</protocol></itemLocation></itemProps></DataProperties><SyncDate>20200710</SyncDate><SyncTime>09471100</SyncTime><ModDate>20200710</ModDate><ModTime>09471100</ModTime></Esri><dataIdInfo><envirDesc Sync="TRUE"> Version 6.2 (Build 9200) ; Esri ArcGIS 10.8.0.12790</envirDesc><dataLang><languageCode value="eng" Sync="TRUE"></languageCode><countryCode value="USA" Sync="TRUE"></countryCode></dataLang><idCitation><resTitle Sync="TRUE">att22_SimplPoly0.5</resTitle><presForm><PresFormCd value="005" Sync="TRUE"></PresFormCd></presForm></idCitation><spatRpType><SpatRepTypCd value="001" Sync="TRUE"></SpatRepTypCd></spatRpType></dataIdInfo><mdLang><languageCode value="eng" Sync="TRUE"></languageCode><countryCode value="USA" Sync="TRUE"></countryCode></mdLang><mdChar><CharSetCd value="004" Sync="TRUE"></CharSetCd></mdChar><distInfo><distFormat><formatName Sync="TRUE">Shapefile</formatName></distFormat><distTranOps><transSize Sync="TRUE">0.000</transSize></distTranOps></distInfo><mdHrLv><ScopeCd value="005" Sync="TRUE"></ScopeCd></mdHrLv><mdHrLvName Sync="TRUE">dataset</mdHrLvName><spatRepInfo><VectSpatRep><geometObjs Name="att22_SimplPoly0.5"><geoObjTyp><GeoObjTypCd value="002" Sync="TRUE"></GeoObjTypCd></geoObjTyp><geoObjCnt Sync="TRUE">0</geoObjCnt></geometObjs><topLvl><TopoLevCd value="001" Sync="TRUE"></TopoLevCd></topLvl></VectSpatRep></spatRepInfo><spdoinfo><ptvctinf><esriterm Name="att22_SimplPoly0.5"><efeatyp Sync="TRUE">Simple</efeatyp><efeageom code="4" Sync="TRUE"></efeageom><esritopo Sync="TRUE">FALSE</esritopo><efeacnt Sync="TRUE">0</efeacnt><spindex Sync="TRUE">FALSE</spindex><linrefer Sync="TRUE">FALSE</linrefer></esriterm></ptvctinf></spdoinfo><eainfo><detailed Name="att22_SimplPoly0.5"><enttyp><enttypl Sync="TRUE">att22_SimplPoly0.5</enttypl><enttypt Sync="TRUE">Feature Class</enttypt><enttypc Sync="TRUE">0</enttypc></enttyp><attr><attrlabl Sync="TRUE">FID</attrlabl><attalias Sync="TRUE">FID</attalias><attrtype Sync="TRUE">OID</attrtype><attwidth Sync="TRUE">4</attwidth><atprecis Sync="TRUE">0</atprecis><attscale Sync="TRUE">0</attscale><attrdef Sync="TRUE">Internal feature number.</attrdef><attrdefs Sync="TRUE">Esri</attrdefs><attrdomv><udom Sync="TRUE">Sequential unique whole numbers that are automatically generated.</udom></attrdomv></attr><attr><attrlabl Sync="TRUE">Shape</attrlabl><attalias Sync="TRUE">Shape</attalias><attrtype Sync="TRUE">Geometry</attrtype><attwidth Sync="TRUE">0</attwidth><atprecis Sync="TRUE">0</atprecis><attscale Sync="TRUE">0</attscale><attrdef Sync="TRUE">Feature geometry.</attrdef><attrdefs Sync="TRUE">Esri</attrdefs><attrdomv><udom Sync="TRUE">Coordinates defining the features.</udom></attrdomv></attr><attr><attrlabl Sync="TRUE">att22recl</attrlabl><attalias Sync="TRUE">att22recl</attalias><attrtype Sync="TRUE">String</attrtype><attwidth Sync="TRUE">50</attwidth><atprecis Sync="TRUE">0</atprecis><attscale Sync="TRUE">0</attscale></attr></detailed></eainfo><mdDateSt Sync="TRUE">20200710</mdDateSt></metadata>
